proto_models/chart_pb2.py
proto_models/chart_pb2.pyi
proto_models/company_info_pb2.py
proto_models/company_info_pb2.pyi
proto_models/news_pb2.py
proto_models/news_pb2.pyi
proto_models/option_bars_pb2.py
proto_models/option_bars_pb2.pyi
proto_models/option_chain_pb2.py
proto_models/option_chain_pb2.pyi
proto_models/quote_pb2.py
proto_models/quote_pb2.pyi
proto_models/wheelstrategy_pb2.py
proto_models/wheelstrategy_pb2.pyi
proto_models_py-1.2.0.dist-info/METADATA
proto_models_py-1.2.0.dist-info/WHEEL
proto_models_py-1.2.0.dist-info/top_level.txt
proto_models_py-1.2.0.dist-info/RECORD
