Metadata-Version: 2.4
Name: proto-models-py
Version: 1.2.0
Summary: Generated Python protobuf models for trading and financial data
Author-email: Your Name <your.email@example.com>
License-Expression: MIT
Project-URL: Homepage, https://github.com/yourusername/protos
Project-URL: Repository, https://github.com/yourusername/protos
Project-URL: Issues, https://github.com/yourusername/protos/issues
Keywords: protobuf,trading,finance,models
Classifier: Development Status :: 4 - Beta
Classifier: Intended Audience :: Developers
Classifier: Programming Language :: Python :: 3
Classifier: Programming Language :: Python :: 3.8
Classifier: Programming Language :: Python :: 3.9
Classifier: Programming Language :: Python :: 3.10
Classifier: Programming Language :: Python :: 3.11
Classifier: Topic :: Software Development :: Libraries :: Python Modules
Requires-Python: >=3.8
Requires-Dist: protobuf>=4.21.0
